slurm_watchdog/__init__.py
slurm_watchdog/dummyjob.py
slurm_watchdog/main.py
slurm_watchdog-0.1.0.dist-info/METADATA
slurm_watchdog-0.1.0.dist-info/WHEEL
slurm_watchdog-0.1.0.dist-info/entry_points.txt
slurm_watchdog-0.1.0.dist-info/RECORD
