Metadata-Version: 2.3
Name: slurm-watchdog
Version: 0.1.0
Summary: Watches a SLURM job and aborts it if it stops outputting to a logfile
Requires-Python: >=3.10
